bitscope/__init__.py
bitscope/channel.py
bitscope/device.py
bitscope/metadata.py
bitscope/scope.py
bitscope/trace.py
bitscope-0.0.3.dist-info/DESCRIPTION.rst
bitscope-0.0.3.dist-info/METADATA
bitscope-0.0.3.dist-info/RECORD
bitscope-0.0.3.dist-info/WHEEL
bitscope-0.0.3.dist-info/metadata.json
bitscope-0.0.3.dist-info/top_level.txt
utils/__init__.py
utils/logger.py
