Metadata-Version: 2.0
Name: bitscope
Version: 0.0.3
Summary: python package for bitscope micro
Home-page: https://github.com/codenio/bitscope
Author: Aananth K
Author-email: aananthraj1995@gmail.com
License: GPL-3.0
Platform: UNKNOWN
Requires-Dist: bitlib
